{  "@context": "http://schema.org",  "name": "何以为家 كفرناحوم",  "url": "/subject/30170448/",  "image": "https://img1.doubanio.com/view/photo/s_ratio_poster/public/p2555295759.webp",  "director":   [    {      "@type": "Person",      "url": "/celebrity/1275745/",      "name": "娜丁·拉巴基 Nadine Labaki"    }  ],  "author":   [    {      "@type": "Person",      "url": "/celebrity/1275745/",      "name": "娜丁·拉巴基 Nadine Labaki"    }    ,    {      "@type": "Person",      "url": "/celebrity/1395542/",      "name": "吉哈德·霍加里 Jihad Hojeily"    }    ,    {      "@type": "Person",      "url": "/celebrity/1395543/",      "name": "米歇尔·凯斯沃尼 Michelle Keserwany"    }    ,    {      "@type": "Person",      "url": "/celebrity/1411931/",      "name": "乔治斯·哈巴兹 Georges Khabbaz"    }    ,    {      "@type": "Person",      "url": "/celebrity/1393709/",      "name": "哈立德·穆扎纳 Khaled Mouzanar"    }  ],  "actor":   [    {      "@type": "Person",      "url": "/celebrity/1393813/",      "name": "赞恩·阿尔·拉菲亚 Zain al-Rafeea"    }    ,    {      "@type": "Person",      "url": "/celebrity/1411924/",      "name": "约丹诺斯·希费罗 Yordanos Shiferaw"    }    ,    {      "@type": "Person",      "url": "/celebrity/1395545/",      "name": "博鲁瓦蒂夫·特雷杰·班科尔 Boluwatife Treasure Bankole"    }    ,    {      "@type": "Person",      "url": "/celebrity/1411925/",      "name": "卡萨尔·艾尔·哈达德 Kawsar Al Haddad"    }    ,    {      "@type": "Person",      "url": "/celebrity/1411926/",      "name": "法迪·尤瑟夫 Fadi Yousef"    }    ,    {      "@type": "Person",      "url": "/celebrity/1411927/",      "name": "海塔·塞德拉·伊扎姆 Haita &#39;Cedra&#39; Izzam"    }    ,    {      "@type": "Person",      "url": "/celebrity/1411928/",      "name": "阿拉·乔什涅 Alaa Chouchnieh"    }    ,    {      "@type": "Person",      "url": "/celebrity/1275745/",      "name": "娜丁·拉巴基 Nadine Labaki"    }    ,    {      "@type": "Person",      "url": "/celebrity/1411929/",      "name": "埃利亚斯·库利 Elias Khoury"    }    ,    {      "@type": "Person",      "url": "/celebrity/1411930/",      "name": "努尔·艾尔·侯赛尼 Nour El Husseini"    }  ],  "datePublished": "2018-05-17",  "genre": ["\u5267\u60c5"],  "duration": "PT2H6M",  "description": "法庭上，十二岁的男孩赞恩向法官状告他的亲生父母，原因是，他们给了他生命。是什么样的经历让一个孩子做出如此不可思议的举动？故事中，赞恩的父母在无力抚养和教育的状况下依然不停生育，作为家中的长子赞恩，弱小...",  "@type": "Movie",  "aggregateRating": {    "@type": "AggregateRating",    "ratingCount": "759343",    "bestRating": "10",    "worstRating": "2",    "ratingValue": "9.1"  }}