{  "@context": "http://schema.org",  "name": "怪兽电力公司 Monsters, Inc.",  "url": "/subject/1291579/",  "image": "https://img1.doubanio.com/view/photo/s_ratio_poster/public/p2513247938.webp",  "director":   [    {      "@type": "Person",      "url": "/celebrity/1022803/",      "name": "彼特·道格特 Pete Docter"    }    ,    {      "@type": "Person",      "url": "/celebrity/1032493/",      "name": "大卫·斯沃曼 David Silverman"    }    ,    {      "@type": "Person",      "url": "/celebrity/1022678/",      "name": "李·昂克里奇 Lee Unkrich"    }  ],  "author":   [    {      "@type": "Person",      "url": "/celebrity/1036450/",      "name": "安德鲁·斯坦顿 Andrew Stanton"    }    ,    {      "@type": "Person",      "url": "/celebrity/1284753/",      "name": "丹尼尔·吉尔森 Daniel Gerson"    }    ,    {      "@type": "Person",      "url": "/celebrity/1277721/",      "name": "罗伯特·L·贝尔德 Robert L. Baird"    }    ,    {      "@type": "Person",      "url": "/celebrity/1327382/",      "name": "瑞特·里斯 Rhett Reese"    }    ,    {      "@type": "Person",      "url": "/celebrity/1171775/",      "name": "乔纳森·罗伯特  Jonathan Roberts"    }    ,    {      "@type": "Person",      "url": "/celebrity/1022803/",      "name": "彼特·道格特 Pete Docter"    }    ,    {      "@type": "Person",      "url": "/celebrity/1358669/",      "name": "杰夫·皮金 Jeff Pidgeon"    }    ,    {      "@type": "Person",      "url": "/celebrity/1358670/",      "name": "吉尔·卡尔顿 Jill Culton"    }    ,    {      "@type": "Person",      "url": "/celebrity/1028474/",      "name": "拉夫·埃格尔斯顿 Ralph Eggleston"    }  ],  "actor":   [    {      "@type": "Person",      "url": "/celebrity/1017898/",      "name": "约翰·古德曼 John Goodman"    }    ,    {      "@type": "Person",      "url": "/celebrity/1031893/",      "name": "比利·克里斯托 Billy Crystal"    }    ,    {      "@type": "Person",      "url": "/celebrity/1093841/",      "name": "玛丽·吉布斯 Mary Gibbs"    }    ,    {      "@type": "Person",      "url": "/celebrity/1054409/",      "name": "史蒂夫·布西密 Steve Buscemi"    }    ,    {      "@type": "Person",      "url": "/celebrity/1049562/",      "name": "詹姆斯·柯本 James Coburn"    }    ,    {      "@type": "Person",      "url": "/celebrity/1049519/",      "name": "詹妮弗·提莉 Jennifer Tilly"    }    ,    {      "@type": "Person",      "url": "/celebrity/1294383/",      "name": "鲍勃·彼德森 Bob Peterson"    }    ,    {      "@type": "Person",      "url": "/celebrity/1002680/",      "name": "约翰·拉岑贝格 John Ratzenberger"    }    ,    {      "@type": "Person",      "url": "/celebrity/1019054/",      "name": "弗兰克·奥兹 Frank Oz"    }    ,    {      "@type": "Person",      "url": "/celebrity/1284753/",      "name": "丹尼尔·吉尔森 Daniel Gerson"    }    ,    {      "@type": "Person",      "url": "/celebrity/1049523/",      "name": "邦尼·亨特 Bonnie Hunt"    }    ,    {      "@type": "Person",      "url": "/celebrity/1040769/",      "name": "杰克·安杰尔 Jack Angel"    }    ,    {      "@type": "Person",      "url": "/celebrity/1065559/",      "name": "塞缪尔·洛德·布莱克 Samuel Lord Black"    }    ,    {      "@type": "Person",      "url": "/celebrity/1153427/",      "name": "史蒂夫·萨斯坎德 Steve Susskind"    }    ,    {      "@type": "Person",      "url": "/celebrity/1022678/",      "name": "李·昂克里奇 Lee Unkrich"    }    ,    {      "@type": "Person",      "url": "/celebrity/1320458/",      "name": "李立宏 Lihong Li"    }    ,    {      "@type": "Person",      "url": "/celebrity/1315938/",      "name": "王伟忠 Wei-zhong Wang"    }    ,    {      "@type": "Person",      "url": "/celebrity/1040504/",      "name": "华莱士·肖恩 Wallace Shawn"    }    ,    {      "@type": "Person",      "url": "/celebrity/1317127/",      "name": "黄子佼 Mickey Huang"    }    ,    {      "@type": "Person",      "url": "/celebrity/1331134/",      "name": "胡立成 Licheng Hu"    }    ,    {      "@type": "Person",      "url": "/celebrity/1348618/",      "name": "雪莉·琳恩 Sherry Lynn"    }    ,    {      "@type": "Person",      "url": "/celebrity/1283454/",      "name": "比尔·法玛尔 Bill Farmer"    }  ],  "datePublished": "2001-11-02",  "genre": ["\u513f\u7ae5", "\u559c\u5267", "\u52a8\u753b", "\u5947\u5e7b", "\u5192\u9669"],  "duration": "PT1H32M",  "description": "我们不知道，在那样的世界里住着那样一群怪物。他们长相滑稽，却必须装作狰狞。因为，在夜深的时候，他们要悄悄的出现在孩子的衣橱里，吓唬刚刚甜美睡去的宝宝。一切，只因为他们是怪物电力公司的员工，而孩子的尖叫...",  "@type": "Movie",  "aggregateRating": {    "@type": "AggregateRating",    "ratingCount": "501482",    "bestRating": "10",    "worstRating": "2",    "ratingValue": "8.7"  }}